burstfit/__init__.py
burstfit/curvefit.py
burstfit/data.py
burstfit/fit.py
burstfit/io.py
burstfit/mcmc.py
burstfit/model.py
burstfit/utils/__init__.py
burstfit/utils/astro.py
burstfit/utils/functions.py
burstfit/utils/math.py
burstfit/utils/misc.py
burstfit/utils/plotter.py
burstfit-0.1.0.dist-info/LICENSE
burstfit-0.1.0.dist-info/METADATA
burstfit-0.1.0.dist-info/WHEEL
burstfit-0.1.0.dist-info/top_level.txt
burstfit-0.1.0.dist-info/RECORD
